depsdev/__init__.py
depsdev/__main__.py
depsdev/_version.py
depsdev/base.py
depsdev/osv.py
depsdev/py.typed
depsdev/v3.py
depsdev/v3alpha.py
depsdev/cli/__init__.py
depsdev/cli/purl.py
depsdev/cli/vuln.py
depsdev-0.0.5.dist-info/METADATA
depsdev-0.0.5.dist-info/WHEEL
depsdev-0.0.5.dist-info/entry_points.txt
depsdev-0.0.5.dist-info/licenses/LICENSE.txt
depsdev-0.0.5.dist-info/RECORD
